example/batcher/__init__.py
furious/__init__.py
furious/_pkg_meta.py
furious/async.py
furious/batcher.py
furious/config.py
furious/errors.py
furious/job_utils.py
furious/processors.py
furious/context/__init__.py
furious/context/_execution.py
furious/context/_local.py
furious/context/auto_context.py
furious/context/context.py
furious/extras/__init__.py
furious/extras/insert_task_handlers.py
furious/extras/xsrf.py
furious/extras/appengine/__init__.py
furious/extras/appengine/ndb_persistence.py
furious/handlers/__init__.py
furious/handlers/webapp.py
furious/test_stubs/__init__.py
furious/test_stubs/appengine/__init__.py
furious/test_stubs/appengine/queues.py
furious/tests/__init__.py
furious/tests/test_async.py
furious/tests/test_batcher.py
furious/tests/test_config.py
furious/tests/test_job_utils.py
furious/tests/test_processors.py
furious/tests/context/__init__.py
furious/tests/context/test_auto_context.py
furious/tests/context/test_context.py
furious/tests/context/test_execution_context.py
furious/tests/context/test_local.py
furious/tests/dummy_module/__init__.py
furious/tests/dummy_module/dumb.py
furious/tests/extras/__init__.py
furious/tests/extras/test_insert_task_handlers.py
furious/tests/extras/test_xsrf.py
furious/tests/extras/appengine/__init__.py
furious/tests/extras/appengine/test_ndb_persistence.py
furious/tests/handlers/__init__.py
furious/tests/handlers/test__init__.py
furious/tests/test_stubs/__init__.py
furious/tests/test_stubs/appengine/__init__.py
furious/tests/test_stubs/appengine/test_queues.py
furious-1.6.5.dist-info/LICENSE
furious-1.6.5.dist-info/METADATA
furious-1.6.5.dist-info/NOTICE
furious-1.6.5.dist-info/WHEEL
furious-1.6.5.dist-info/top_level.txt
furious-1.6.5.dist-info/RECORD
